LICENSE.txt
README.md
setup.py
rp2040/__init__.py
rp2040/base.py
rp2040/pico.py
rp2040/zero.py
rp2040/algorithm/PID.py
rp2040/algorithm/__init__.py
rp2040/drives/__init__.py
rp2040/drives/HC/__init__.py
rp2040/message/__init__.py
rp2040/message/drive.py
rp2040/message/protocol.py
rp2040/oled/__init__.py
rp2040/oled/ssd1306.py
rp2040/powerhouse/__init__.py
rp2040/powerhouse/blendComposition.py
rp2040/powerhouse/engine.py
rp2040/powerhouse/engineGroup.py
rp2040/powerhouse/servo.py
rp2040/powerhouse/servoGroup.py
rp2040/sensor/__init__.py
rp2040/sensor/hcsr04.py
rp2040/sensor/mpu6050.py
rp2040_tools.egg-info/PKG-INFO
rp2040_tools.egg-info/SOURCES.txt
rp2040_tools.egg-info/dependency_links.txt
rp2040_tools.egg-info/top_level.txt