Metadata-Version: 2.1
Name: rp2040-tools
Version: 0.0.8
Summary: Some tools for RP2040
Home-page: 
Author: 曾钦李
Author-email: 1838696034@qq.com
Maintainer: 
Maintainer-email: 
License: MIT License
Classifier: License :: OSI Approved :: MIT License
License-File: LICENSE.txt
